Metadata-Version: 2.1
Name: google-dataproc-templates
Version: 0.1.0
Summary: Google Dataproc templates written in Python
Home-page: https://github.com/GoogleCloudPlatform/dataproc-templates
License: Apache 2.0
Platform: Posix; MacOS X; Windows
Requires-Python: >=3.7
Requires-Dist: pyspark (>=3.2.0)
Requires-Dist: google-cloud-bigquery (>=3.4.0)
